{
  "resourceType" : "Specimen",
  "id" : "SpecimenExample",
  "meta" : {
    "profile" : ["https://fhir.cqdg.ca/StructureDefinition/cqdg-specimen"],
    "tag" : [{
      "code" : "CAG"
    }]
  },
  "text" : {
    "status" : "extensions",
    "div" : "<div xmlns=\"http://www.w3.org/1999/xhtml\"><p><b>Generated Narrative: Specimen</b><a name=\"SpecimenExample\"> </a></p><div style=\"display: inline-block; background-color: #d9e0e7; padding: 6px; margin: 4px; border: 1px solid #8da1b4; border-radius: 5px; line-height: 60%\"><p style=\"margin-bottom: 0px\">Resource Specimen &quot;SpecimenExample&quot; </p><p style=\"margin-bottom: 0px\">Profile: <a href=\"StructureDefinition-cqdg-specimen.html\">Ferlab.bio StructureDefinition/cqdg-specimen</a></p><p style=\"margin-bottom: 0px\">Tag: <span title=\"{null null}\"/></p></div><p><b>Ferlab.bio Extension/age-at-event</b>: Antenatal <span style=\"background: LightGoldenRodYellow; margin: 4px; border: 1px solid khaki\"> (<a href=\"CodeSystem-age-at-onset.html\">Ferlab.bio CodeSystem/age-at-onset</a>#HP:0030674)</span></p><p><b>identifier</b>: id:\u00a0SpecimenExample, id:\u00a0cag_sp_25565\u00a0(use:\u00a0SECONDARY)</p><p><b>type</b>: DNA <span style=\"background: LightGoldenRodYellow; margin: 4px; border: 1px solid khaki\"> (<a href=\"CodeSystem-qc-sample-type.html\">Ferlab.bio CodeSystem/sample-type</a>#NCIT:C12434)</span></p><p><b>subject</b>: <a href=\"Patient-PatientExample.html\">Patient/PatientExample</a></p></div>"
  },
  "extension" : [{
    "url" : "https://fhir.cqdg.ca/StructureDefinition/AgeAtEvent",
    "valueCodeableConcept" : {
      "coding" : [{
        "system" : "http://purl.obolibrary.org/obo/hp.owl",
        "code" : "HP:0030674"
      }]
    }
  }],
  "identifier" : [{
    "system" : "https://fhir.cqdg.ca/fhir/Specimen",
    "value" : "SpecimenExample"
  },
  {
    "use" : "secondary",
    "value" : "cag_sp_25565"
  }],
  "type" : {
    "coding" : [{
      "system" : "http://purl.obolibrary.org/obo/ncit.owl",
      "code" : "NCIT:C12434",
      "display" : "DNA"
    }]
  },
  "subject" : {
    "reference" : "Patient/PatientExample"
  }
}